anqa/db/__init__.py
anqa/db/_version.py
anqa/db/dialects/__init__.py
anqa/db/dialects/postgres.py
anqa/db/dialects/sqlite.py
anqa/db/factory.py
anqa/db/function_elements.py
anqa/db/mixins.py
anqa/db/orm.py
anqa/db/py.typed
anqa/db/repository.py
anqa/db/settings.py
anqa/db/types.py
anqa_db-0.0.1.dist-info/METADATA
anqa_db-0.0.1.dist-info/WHEEL
anqa_db-0.0.1.dist-info/RECORD
